snakemake_executor_plugin_slurm_gustave_roussy/__init__.py
snakemake_executor_plugin_slurm_gustave_roussy/utils.py
snakemake_executor_plugin_slurm_gustave_roussy-0.6.0.dist-info/METADATA
snakemake_executor_plugin_slurm_gustave_roussy-0.6.0.dist-info/WHEEL
snakemake_executor_plugin_slurm_gustave_roussy-0.6.0.dist-info/licenses/LICENSE
snakemake_executor_plugin_slurm_gustave_roussy-0.6.0.dist-info/RECORD
